odoo_helper/__init__.py
odoo_helper/api.py
tests/__init__.py
tests/connectivity.py
odoo_helper-0.1.1.dist-info/LICENSE
odoo_helper-0.1.1.dist-info/METADATA
odoo_helper-0.1.1.dist-info/WHEEL
odoo_helper-0.1.1.dist-info/top_level.txt
odoo_helper-0.1.1.dist-info/RECORD
